http_logger/__init__.py
http_logger/handlers.py
http_logger-0.0.1.dist-info/LICENSE
http_logger-0.0.1.dist-info/METADATA
http_logger-0.0.1.dist-info/WHEEL
http_logger-0.0.1.dist-info/top_level.txt
http_logger-0.0.1.dist-info/RECORD
