Metadata-Version: 2.1
Name: http-logger
Version: 0.0.1
Summary: Log over http with an auth token
Home-page: https://github.com/amp89/http_logger
Author: Alex Peterson
Author-email: alexander.peterson89@gmail.com
License: UNKNOWN
Platform: UNKNOWN
Classifier: Programming Language :: Python :: 3
Classifier: License :: OSI Approved :: MIT License
Classifier: Operating System :: OS Independent
Requires-Python: >=3.6
